{
  "_fv": 15,
  "_type": "food",
  "definition": {
    "renderType": 0,
    "texture": "amendoim_stew",
    "customModelName": "Normal",
    "name": "Amendoim Stew",
    "rarity": "COMMON",
    "specialInfo": [],
    "creativeTab": {
      "value": "FOOD"
    },
    "stackSize": 1,
    "nutritionalValue": 6,
    "saturation": 1.6,
    "eatingSpeed": 32,
    "resultItem": {
      "value": "Items.BOWL"
    },
    "forDogs": false,
    "isAlwaysEdible": false,
    "animation": "drink",
    "hasGlow": false,
    "onEaten": {
      "name": "AmendoimStewProcedure"
    }
  }
}